feiyan/__init__.py
feiyan/client.py
feiyan/fy_client.py
feiyan/auth/__init__.py
feiyan/auth/signature_composer.py
feiyan/common/__init__.py
feiyan/common/constant.py
feiyan/http/__init__.py
feiyan/http/api.py
feiyan/http/fy_request.py
feiyan/http/request.py
feiyan_py3-1.0.2.dist-info/METADATA
feiyan_py3-1.0.2.dist-info/RECORD
feiyan_py3-1.0.2.dist-info/WHEEL
feiyan_py3-1.0.2.dist-info/top_level.txt
