Metadata-Version: 2.1
Name: feiyan-py3
Version: 1.0.2
Summary: iot feiyan package
Home-page: https://github.com/jerrygaoyang/feiyan_py3
Author: jerrygaoyang
Author-email: 917616767@qq.com
License: UNKNOWN
Platform: UNKNOWN
Requires-Dist: requests
